<?xml version="1.0" encoding="utf-8" ?>
<hibernate-mapping xmlns="urn:nhibernate-mapping-2.2"
                   namespace="WangYc.Models.PO"
                   assembly="WangYc.Models">
  <class name="PurchaseOrderDetail" abstract="true" table="PurchaseOrderDetail" >
    <!--主键ID必须命名为Id-->
    <id name="Id" column="Id" type="int" unsaved-value="0">
      <generator class="identity" />
      <!--generator：主键的生成策略，unsaved-value：主键的默认值， -->
    </id>
    <many-to-one name="PurchaseOrder" class="PurchaseOrder" column="PurchaseOrderId" lazy="false" fetch="select"></many-to-one>
    <many-to-one name="Product" class="WangYc.Models.SD.Product" column="ProductId" lazy="false" fetch="select"></many-to-one>
    <property name="Qty" column="Qty"></property>
    <property name="UnitPrice" column="UnitPrice"></property>
    <property name="Note" column="Note"></property>
    <property name="IsValid" column="IsValid"></property>
    <property name="CreateUserId" column="CreateUserId"></property>
    <property name="CreateDate" column="CreateDate"></property>

  </class>
</hibernate-mapping>